refactor_app/__init__.py
refactor_app/audio_main.py
refactor_app/core/__init__.py
refactor_app/core/config.py
refactor_app/core/database/__init__.py
refactor_app/core/database/minio.py
refactor_app/core/database/sqlite.py
refactor_app/core/logging_config.py
refactor_app/core/repositories/__init__.py
refactor_app/core/repositories/base_sensor_repository.py
refactor_app/core/services/__init__.py
refactor_app/core/services/base_noise_equivalent.py
refactor_app/core/services/base_noise_sensor_service.py
refactor_app/core/services/base_sensor_service.py
refactor_app/core/services/noise_event.py
refactor_app/core/services/raw_record_data.py
refactor_app/noise_main.py
refactor_app/repositories/__init__.py
refactor_app/repositories/noise/__init__.py
refactor_app/repositories/noise/audio_converter_repository.py
refactor_app/repositories/noise/event_repository.py
refactor_app/repositories/noise/minio_repository.py
refactor_app/repositories/noise/noise_record_repository.py
refactor_app/repositories/noise/noise_repository.py
refactor_app/repositories/noise/notification_repository.py
refactor_app/repositories/producer_repository/__init__.py
refactor_app/schemas/__init__.py
refactor_app/schemas/audio_converter_schemas.py
refactor_app/schemas/noise_schemas.py
refactor_app/services/__init__.py
refactor_app/services/audio_converter_services/__init__.py
refactor_app/services/audio_converter_services/audio_converter_service.py
refactor_app/services/dust_services/__init__.py
refactor_app/services/noise_services/__init__.py
refactor_app/services/noise_services/event_service.py
refactor_app/services/noise_services/nti_service.py
refactor_app/services/noise_services/umik_service.py
refactor_app/utils/__init__.py
refactor_app/utils/calculate_utils.py
refactor_app/utils/nti_utils.py
refactor_app/utils/system_utils.py
refactor_app/utils/umik_utils.py
ecoflight1_producer-0.1.1.dist-info/METADATA
ecoflight1_producer-0.1.1.dist-info/WHEEL
ecoflight1_producer-0.1.1.dist-info/entry_points.txt
ecoflight1_producer-0.1.1.dist-info/RECORD
